{
  "parent": "minecraft:recipes/root",
  "criteria": {
    "has_deepslate_aluminium_ore": {
      "conditions": {
        "items": [
          {
            "items": "simpleoregen:deepslate_aluminium_ore"
          }
        ]
      },
      "trigger": "minecraft:inventory_changed"
    },
    "has_the_recipe": {
      "conditions": {
        "recipe": "simpleoregen:aluminium_ingot_from_smelting_deepslate_aluminium_ore"
      },
      "trigger": "minecraft:recipe_unlocked"
    }
  },
  "requirements": [
    [
      "has_the_recipe",
      "has_deepslate_aluminium_ore"
    ]
  ],
  "rewards": {
    "recipes": [
      "simpleoregen:aluminium_ingot_from_smelting_deepslate_aluminium_ore"
    ]
  }
}